nucliadb_admin_assets/3rdpartylicenses.txt
nucliadb_admin_assets/623.3874b9ad254bcdce.js
nucliadb_admin_assets/__init__.py
nucliadb_admin_assets/index.html
nucliadb_admin_assets/main.d8d6d77b386d877d.js
nucliadb_admin_assets/polyfills.1d6ad259bb52c34f.js
nucliadb_admin_assets/runtime.f727754566c1cfa2.js
nucliadb_admin_assets/source-code-pro-v14-latin-regular.c54f7f16da733fd8.woff
nucliadb_admin_assets/source-code-pro-v14-latin-regular.e7bb30b550ed09e8.woff2
nucliadb_admin_assets/styles.48b03416c73f34b6.css
nucliadb_admin_assets/assets/glyphs-sprite.svg
nucliadb_admin_assets/assets/connector-logos/algolia.svg
nucliadb_admin_assets/assets/connector-logos/brightcove.svg
nucliadb_admin_assets/assets/connector-logos/confluence.svg
nucliadb_admin_assets/assets/connector-logos/dropbox.svg
nucliadb_admin_assets/assets/connector-logos/folder.svg
nucliadb_admin_assets/assets/connector-logos/gcs.svg
nucliadb_admin_assets/assets/connector-logos/gdrive.svg
nucliadb_admin_assets/assets/connector-logos/nucliacloud.svg
nucliadb_admin_assets/assets/connector-logos/onedrive.svg
nucliadb_admin_assets/assets/connector-logos/rss.svg
nucliadb_admin_assets/assets/connector-logos/s3.svg
nucliadb_admin_assets/assets/connector-logos/sharepoint.svg
nucliadb_admin_assets/assets/connector-logos/sitefinity.svg
nucliadb_admin_assets/assets/connector-logos/sitemap.svg
nucliadb_admin_assets/assets/deployment/app-config.json
nucliadb_admin_assets/assets/deployment/app-config.json.bak
nucliadb_admin_assets/assets/fonts/source-code-pro/source-code-pro-v14-latin-regular.woff
nucliadb_admin_assets/assets/fonts/source-code-pro/source-code-pro-v14-latin-regular.woff2
nucliadb_admin_assets/assets/fonts/videoagular/Videogular.json
nucliadb_admin_assets/assets/fonts/videoagular/videogular.woff
nucliadb_admin_assets/assets/i18n/common/ca.json
nucliadb_admin_assets/assets/i18n/common/en.json
nucliadb_admin_assets/assets/i18n/common/es.json
nucliadb_admin_assets/assets/i18n/common/fr.json
nucliadb_admin_assets-1.0.0.post2650.dist-info/METADATA
nucliadb_admin_assets-1.0.0.post2650.dist-info/WHEEL
nucliadb_admin_assets-1.0.0.post2650.dist-info/top_level.txt
nucliadb_admin_assets-1.0.0.post2650.dist-info/zip-safe
nucliadb_admin_assets-1.0.0.post2650.dist-info/RECORD
