Metadata-Version: 2.1
Name: nucliadb-admin-assets
Version: 1.0.0.post2650
Summary: Packaging of NucliaDB admin JS app
Home-page: https://github.com/nuclia/frontend
Author: Nuclia
Author-email: nucliadb@nuclia.com
License: UNKNOWN
Platform: UNKNOWN
